---
layout:     post
title:      枚举
subtitle:   概述
date:       2021-04-14
author:     QuanLi
header-img: img/post-bg-kuaidi.jpg
catalog: true
tags:
    - JavaSE
---

# 枚举

​	enum关键字在 java5 中引入，表示一种特殊类型的类，其总是继承java.lang.Enum类

### 为什么要用枚举

​	枚举在很多时候会和常量拿来对比，可能因为本身我们大量实际**使用枚举的地方就是为了替代常量**。**使用枚举代替常量，代码会更具可读性，允许编译时期进行安全检查，预先记录可接受参数值的列表，避免传入无效值而引起的意外行为。**

下面示例定义一个简单的枚举类型 pizza 订单的状态，共有三种 ORDERED, READY, DELIVERED状态:

~~~java
package shuang.kou.enumdemo.enumtest;

public enum PizzaStatus {
    ORDERED,
    READY, 
    DELIVERED; 
}
~~~

​	**简单来说，我们通过上面的代码避免了定义常量，我们将所有和 pizza 订单的状态的常量都统一放到了一个枚举类型里面。**以前我们定义常量都是： public static final.... 。现在好了，有了枚举，可以把相关的常量分组到一个枚举类型里，而且枚举提供了比常量更多的方法。

~~~Java
System.out.println(PizzaStatus.ORDERED.name());//ORDERED
System.out.println(PizzaStatus.ORDERED);//ORDERED
System.out.println(PizzaStatus.ORDERED.name().getClass());//class java.lang.String
System.out.println(PizzaStatus.ORDERED.getClass());//class shuang.kou.enumdemo.enumtest.PizzaStatus
~~~

### 枚举常用方法

​	如果打算自定义自己的方法，那么必须在enum实例序列的最后添加一个分号。而且 Java 要求必须先定义 enum 实例。

​	在后台管理系统中，肯定有用户角色一说，而且角色一般都是固定的，适合定义成一个枚举：

~~~java
public enum UserRole {

    ROLE_ROOT_ADMIN,  // 系统管理员

    ROLE_ORDER_ADMIN, // 订单管理员

    ROLE_NORMAL       // 普通用户
}
~~~

接下来我们就用这个`UserRole`为例来说明**枚举的所有基本用法**：

~~~Java
UserRole role1 = UserRole.ROLE_ROOT_ADMIN;
UserRole role2 = UserRole.ROLE_ORDER_ADMIN;
UserRole role3 = UserRole.ROLE_NORMAL;

// values()方法：返回所有枚举常量的数组集合
for ( UserRole role : UserRole.values() ) {
    System.out.println(role);
}
// 打印：
// ROLE_ROOT_ADMIN
// ROLE_ORDER_ADMIN
// ROLE_NORMAL

// ordinal()方法：返回枚举常量的序数，注意从0开始
System.out.println( role1.ordinal() ); // 打印0
System.out.println( role2.ordinal() ); // 打印1
System.out.println( role3.ordinal() ); // 打印2

// compareTo()方法：枚举常量间的比较
System.out.println( role1.compareTo(role2) ); //打印-1
System.out.println( role2.compareTo(role3) ); //打印-2
System.out.println( role1.compareTo(role3) ); //打印-2

// name()方法：获得枚举常量的名称
System.out.println( role1.name() ); // 打印ROLE_ROOT_ADMIN
System.out.println( role2.name() ); // 打印ROLE_ORDER_ADMIN
System.out.println( role3.name() ); // 打印ROLE_NORMAL

// valueOf()方法：返回指定名称的枚举常量
System.out.println( UserRole.valueOf( "ROLE_ROOT_ADMIN" ) );
System.out.println( UserRole.valueOf( "ROLE_ORDER_ADMIN" ) );
System.out.println( UserRole.valueOf( "ROLE_NORMAL" ) );
~~~

除此之外，枚举还可以用于`switch`语句中，而且意义更加明确：

~~~Java
UserRole userRole = UserRole.ROLE_ORDER_ADMIN;
switch (userRole) {
    case ROLE_ROOT_ADMIN:  // 比如此处的意义就非常清晰了，比1，2，3这种数字好！
        System.out.println("这是系统管理员角色");
        break;
    case ROLE_ORDER_ADMIN:
        System.out.println("这是订单管理员角色");
        break;
    case ROLE_NORMAL:
        System.out.println("这是普通用户角色");
        break;
}
~~~

### 自定义扩充枚举

​	上面展示的枚举例子非常简单，仅仅是**单值的情形**，而实际项目中用枚举往往是**多值**用法。

​	比如，我想扩充一下上面的`UserRole`枚举，在里面加入 **角色名 -- 角色编码** 的对应关系，这也是实际项目中常用的用法。

​	这时候我们可以在枚举里自定义各种属性、构造函数、甚至各种方法：

~~~Java
public enum UserRole {

    ROLE_ROOT_ADMIN( "系统管理员", 000000 ),
    ROLE_ORDER_ADMIN( "订单管理员", 100000 ),
    ROLE_NORMAL( "普通用户", 200000 ),
    ;

    // 以下为自定义属性
    
    privatefinal String roleName;  //角色名称

    privatefinal Integer roleCode; //角色编码

    // 以下为自定义构造函数
    
    UserRole( String roleName, Integer roleCode ) {
        this.roleName = roleName;
        this.roleCode = roleCode;
    }

    // 以下为自定义方法
    
    public String getRoleName() {
        return this.roleName;
    }

    public Integer getRoleCode() {
        return this.roleCode;
    }

    public static Integer getRoleCodeByRoleName( String roleName ) {
        for( UserRole enums : UserRole.values() ) {
            if( enums.getRoleName().equals( roleName ) ) {
                return enums.getRoleCode();
            }
        }
        return null;
    }

}
~~~

从上述代码可知，在`enum`枚举类中完全可以像在普通`Class`里一样声明属性、构造函数以及成员方法。

### 枚举与设计模式

#### 单例模式

通常，使用类实现 Singleton 模式并非易事，枚举提供了一种实现单例的简便方法。《Effective Java 》和《Java与模式》都非常推荐这种方式，使用这种方式方式实现枚举可以有什么好处呢？

- 这种方法在功能上与公有域方法相近，但是它更加简洁，**无偿提供了序列化机制**，绝对防止多次实例化，**即使是在面对复杂序列化或者反射攻击的时候**。虽然这种方法还没有广泛采用，但是单元素的枚举类型已经成为实现 Singleton的最佳方法。
- 《Java与模式》中，作者这样写道，使用枚举来实现单实例控制会更加简洁，而且无偿地提供了序列化机制，并由JVM从根本上提供保障，绝对防止多次实例化，是更简洁、高效、安全的实现单例的方式。
- 枚举类型是所用单例实现中**唯一一种不会被破坏的单例实现模式**。

~~~Java
public class SingletonObject7 {


    private SingletonObject7(){

    }

    /**
     * 枚举类型是线程安全的，并且只会装载一次
     */
    private enum Singleton{
        INSTANCE;

        private final SingletonObject7 instance;

        Singleton(){
            instance = new SingletonObject7();
        }

        private SingletonObject7 getInstance(){
            return instance;
        }
    }

    public static SingletonObject7 getInstance(){

        return Singleton.INSTANCE.getInstance();
    }
}

~~~

#### 枚举反编译

~~~java
public enum Gender {
    Male,
    Female
}
~~~

​	进行反编译，可以得到一个新的类：

~~~java

public final class Gender extends java.lang.Enum {
  public static final Gender Male;
 
  public static final Gender Female;
 
  public static Gender[] values();
    Code:
       0: getstatic     #1                  // Field $VALUES:[LGender;
       3: invokevirtual #2                  // Method "[LGender;".clone:()Ljava/lang/Object;
       6: checkcast     #3                  // class "[LGender;"
       9: areturn
 
  public static Gender valueOf(java.lang.String);
    Code:
       0: ldc_w         #4                  // class Gender
       3: aload_0
       4: invokestatic  #5                  // Method java/lang/Enum.valueOf:(Ljava/lang/Class;Ljava/lang/String;)Ljava/lang/Enum;
       7: checkcast     #4                  // class Gender
      10: areturn
 
  static {};
    Code:
       0: new           #4                  // class Gender
       3: dup
       4: ldc           #7                  // String Male
       6: iconst_0
       7: invokespecial #8                  // Method "":(Ljava/lang/String;I)V
      10: putstatic     #9                  // Field Male:LGender;
      13: new           #4                  // class Gender
      16: dup
      17: ldc           #10                 // String Female
      19: iconst_1
      20: invokespecial #8                  // Method "":(Ljava/lang/String;I)V
      23: putstatic     #11                 // Field Female:LGender;
      26: iconst_2
      27: anewarray     #4                  // class Gender
      30: dup
      31: iconst_0
      32: getstatic     #9                  // Field Male:LGender;
      35: aastore
      36: dup
      37: iconst_1
      38: getstatic     #11                 // Field Female:LGender;
      41: aastore
      42: putstatic     #1                  // Field $VALUES:[LGender;
      45: return
}
~~~

从上面的字节码能够粗略的知道以下几点;

- Gender 是 final 的
- Gender 继承自 java.lang.Enum 类
- 声明了字段对应的两个 static final Gender 的实例
- **static{} 对所有成员进行初始化**
- **实现了 values() 和 valueOf(String) 静态方法**

有了以上的字节码，我们作进一步还原出 Gender 的普通类大概是这样的：

~~~java
public final class Gender extends java.lang.Enum {
 
  public static final Gender Male;
  public static final Gender Female;
 
  private static final Gender[] $VALUES;
 
  static {
    Male = new Gender("Male", 0);
    Female = new Gender("Female", 1);
 
    $VALUES = new Gender[] {Male, Female};
  }
 
  private Gender(String name, int original) {
    super(name, original)
  }
 
  public static Gender[] values() {
    return $VALUE.clone();
  }
 
  public static Gender valueOf(String name) {
    return Enum.valueOf(Gender.class, name);
  }
}
~~~

#### 防反射

​	枚举类默认继承了 Enum 类，在利用反射调用 newInstance() 时，会判断该类是否是一个枚举类，如果是，则抛出异常。

#### 防反序列化

​	在读入 Singleton 对象时，每个枚举类型和枚举名字都是唯一的，所以在序列化时，仅仅只是对枚举的类型和变量名输出到文件中，在读入文件反序列化成对象时，使用 Enum 类的 valueOf(String name) 方法根据变量的名字查找对应的枚举对象。

所以，在序列化和反序列化的过程中，只是写出和读入了枚举类型和名字，没有任何关于对象的操作。
